{
  "restaurants": [
    {
      "id": "1",
      "name": "Mad About Pizza",
      "description": "Delicious pizzas baked in wood-fired oven. We serve authentic Italian varieties, classic American pizzas, and desi ones too!",
      "cuisines": [
        "Italian",
        "American",
        "Fusion"
      ],
      "opens": "11:00",
      "closes": "23:30",
      "rating": 4.1,
      "numRatings": 125,
      "costForTwo": 600,
      "imageUrl": "/images/restaurants/mad-about-pizza/restaurant.jpg"
    },
    {
      "id": "2",
      "name": "Nachos & Tacos",
      "description": "Hola Amigos! You have arrived at the right place to get some Mexican delicacies. Quesadillas, Burritos, variety of salsas, and much more. Yes, Nachos and Tacos goes without saying!",
      "cuisines": [
        "Mexican",
        "Tex-Mex",
        "Spanish"
      ],
      "opens": "10:00",
      "closes": "22:30",
      "rating": 4.3,
      "numRatings": 89,
      "costForTwo": 450,
      "imageUrl": "/images/restaurants/nachos-and-tacos/restaurant.jpg"
    },
    {
      "id": "3",
      "name": "Pind da Swaad",
      "description": "Robust flavors from the Punjab heartland served with lots of love - that's generous amounts of butter and ghee. We also serve popular chats made with tangy chutneys and savouries.",
      "cuisines": [
        "Punjabi",
        "North Indian",
        "Chats"
      ],
      "opens": "11:00",
      "closes": "23:30",
      "rating": 3.9,
      "numRatings": 254,
      "costForTwo": 500,
      "imageUrl": "/images/restaurants/pind-da-swaad/restaurant.jpg"
    },
    {
      "id": "4",
      "name": "Down South",
      "description": "Healthy breakfast options from the south of India. We serve popular South Indian tiffin items, but specialize in certain cuisines from every state of the south.",
      "cuisines": [
        "South Indian",
        "Malabar",
        "Hyderabad",
        "Mangalore"
      ],
      "opens": "7:30",
      "closes": "22:30",
      "rating": 4.5,
      "numRatings": 150,
      "costForTwo": 200,
      "imageUrl": "/images/restaurants/down-south/restaurant.jpg"
    }
  ],
  "items": [
    {
      "id": "1",
      "restaurantId": 1,
      "name": "Garden Fresh Veggie Pizza",
      "price": 459,
      "description": "An abundance of delicious veggies with less crust - a perfect Garden Fresh Pizza! Jalapenos, Corn, Black Olives, Crunchy Bell Peppers, Tomatoes, Onion & Mozzarella Cheese on an herbed and soft 11-inch crust.",
      "imageUrl": "/images/restaurants/mad-about-pizza/items/pizza-garden-fresh.jpg"
    },
    {
      "id": "2",
      "restaurantId": 1,
      "name": "Classic Margherita Pizza",
      "price": 315,
      "description": "Our Margherita pizza is just about 3 things: Cheese, Cheese and more Cheese! An overload of Mozzarella Cheese finely spread on an herbed, soft 11-inch crust. Must have for every cheese lover.",
      "imageUrl": "/images/restaurants/mad-about-pizza/items/pizza-margherita.jpg"
    },
    {
      "id": "3",
      "restaurantId": 1,
      "name": "Classic Burger",
      "price": 240,
      "description": "All your favorites - barbeque chicken, chicken patties, wrapped onion stuffed with Colby cheese and in the core of the onion ring stuffed with mashed potatoes, cucumber and lots of cheese.",
      "imageUrl": "/images/restaurants/mad-about-pizza/items/burger.jpg"
    },
    {
      "id": "4",
      "restaurantId": 1,
      "name": "Chicken Tikka Pizza",
      "price": 459,
      "description": "An unheard medley of tandoori tikka and melt-in-the-mouth kheema to amaze your taste buds! Classic Chicken Tikka with delicious Chicken Kheema, Onion and Mozzarella Cheese on a soft 11-inch crust.",
      "imageUrl": "/images/restaurants/mad-about-pizza/items/pizza-chicken-tikka.jpg"
    },
    {
      "id": "5",
      "restaurantId": 2,
      "name": "Nachos",
      "price": 120,
      "description": "Fried corn tortilla chips covered with melted cheese and sliced jalapeño peppers. We serve with lots of guacamole so you can have a feast. Among the all time favorite munchies.",
      "imageUrl": "/images/restaurants/nachos-and-tacos/items/nachos.jpg"
    },
    {
      "id": "6",
      "restaurantId": 2,
      "name": "Tacos",
      "price": 160,
      "description": "Small hand-sized corn or wheat tortilla topped with a filling of your choice - popular ones being cheese, chicken, beans and other veggies.",
      "imageUrl": "/images/restaurants/nachos-and-tacos/items/tacos.jpg"
    },
    {
      "id": "7",
      "restaurantId": 2,
      "name": "Burrito",
      "price": 120,
      "description": "A flour tortilla wrap filled with a savory filling - cooked beans, vegetables, lettuce and tomatoes, cheese, and condiments such as salsa, pico de gallo, and guacamole.",
      "imageUrl": "/images/restaurants/nachos-and-tacos/items/burrito.jpg"
    },
    {
      "id": "8",
      "restaurantId": 2,
      "name": "Fajitas",
      "price": 240,
      "description": "Grilled chicken with stripped peppers, onions, shredded lettuce, sour cream, guacamole, salsa, pico de gallo, and diced tomatoes, served on a flour or corn tortilla.",
      "imageUrl": "/images/restaurants/nachos-and-tacos/items/fajitas.jpg"
    },
    {
      "id": "9",
      "restaurantId": 2,
      "name": "Quesadilla",
      "price": 200,
      "description": "Tortilla filled with cheese, spices, and veggies, and cooked on a griddle. A corn tortilla is used (authentic), but we can also make it with a flour tortilla on request.",
      "imageUrl": "/images/restaurants/nachos-and-tacos/items/quesadilla.jpg"
    },
    {
      "id": "10",
      "restaurantId": 3,
      "name": "Gajar Halwa",
      "price": 120,
      "description": "Grated carrots cooked with a combination of milk, sugar, milk solids (khoya), clarfied butter (ghee) and seasoned with dry fruits like raisins, cashews and pistachios. Must try for those with a sweet tooth.",
      "imageUrl": "/images/restaurants/pind-da-swaad/items/gajar-halwa.jpg"
    },
    {
      "id": "11",
      "restaurantId": 3,
      "name": "Samosa",
      "price": 25,
      "description": "A triangular-shaped fried pastry with a savory filling of potatoes, peas cooked to a semi-mash and seasoned with spices. Served with mint and tamarind-date chutneys.",
      "imageUrl": "/images/restaurants/pind-da-swaad/items/samosa.jpg"
    },
    {
      "id": "12",
      "restaurantId": 3,
      "name": "Kachori",
      "price": 30,
      "description": "Deep fried bread made with ground black gram (urad) and green gram (moong) combination, sauteed along with spices and filled into a cover of maida. It is fried over a slow flame making it extremely crispy and savory.",
      "imageUrl": "/images/restaurants/pind-da-swaad/items/kachori.jpg"
    },
    {
      "id": "13",
      "restaurantId": 3,
      "name": "Punjabi Thali",
      "price": 240,
      "description": "Choose this is you cannot make up your mind! It has all the quintessential Punjabi delicacies - dal makhni, paneer butter masala, rajma, raita served with butter naan and rice. For desserts and accompaniments you get phirni and lassi.",
      "imageUrl": "/images/restaurants/pind-da-swaad/items/punjabi-thali.jpg"
    },
    {
      "id": "14",
      "restaurantId": 4,
      "name": "Idly",
      "price": 40,
      "description": "Steamed rice and black gram (urad dal) pancake served with copious amunts of freshly ground coconut chutney tempered with mustard seasoning. One of the South Indian breakfast classics.",
      "imageUrl": "/images/restaurants/down-south/items/idly-chutney.jpg"
    },
    {
      "id": "15",
      "restaurantId": 4,
      "name": "Masala Dosa",
      "price": 60,
      "description": "Thin and crispy rice and black gram (urad dal) pancake cooked over a griddle, and filled with spicy potato and onion curry that is tempered with a typical seasoning of mustard, curry leaves, green chillies and ginger.",
      "imageUrl": "/images/restaurants/down-south/items/masala-dosa.jpg"
    },
    {
      "id": "16",
      "restaurantId": 4,
      "name": "Medu vada",
      "price": 120,
      "description": "Fluffy and crispy fried savory snack made of black gram batter, mixed with chillies, giner, curry leaves and asafoetida and deep-fried. Served with chutney and sambhar.",
      "imageUrl": "/images/restaurants/down-south/items/medu-vada.jpg"
    },
    {
      "id": "17",
      "restaurantId": 4,
      "name": "Idiappam",
      "price": 60,
      "description": "Steamed string hoppers made from rice and serve along with a mildly spiced and flavorful vegetable stew, and sweetened coconut milk.",
      "imageUrl": "/images/restaurants/down-south/items/idiappam.jpg"
    },
    {
      "id": "18",
      "restaurantId": 4,
      "name": "Goli Baje",
      "price": 30,
      "description": "From the Konkan region comes this this dish of fried dough balls made from refined flour (maida) and sour curd, seasoned with ginger, green chillies, curry leaves, asafoetida. A hit among our patrons.",
      "imageUrl": "/images/restaurants/down-south/items/goli-baje.jpg"
    },
    {
      "name": "Poori Saagu",
      "price": 45,
      "description": "Thin bread made from whole wheat fried till its puffed up. It is served in Karnataka with a spicy mix vegetable curry cooked in a coconut base. Best enjoyed hot and a favorite breakfast item.",
      "imageUrl": "/images/restaurants/down-south/items/poori-sagu.jpg",
      "restaurantId": 1,
      "id": "19"
    },
    {
      "name": "Poori Saagu",
      "price": 45,
      "description": "Thin bread made from whole wheat fried till its puffed up. It is served in Karnataka with a spicy mix vegetable curry cooked in a coconut base. Best enjoyed hot and a favorite breakfast item.",
      "imageUrl": "/images/restaurants/down-south/items/poori-sagu.jpg",
      "restaurantId": 1,
      "id": "20"
    },
    {
      "name": "Poori Saagu",
      "price": 45,
      "description": "Thin bread made from whole wheat fried till its puffed up. It is served in Karnataka with a spicy mix vegetable curry cooked in a coconut base. Best enjoyed hot and a favorite breakfast item.",
      "imageUrl": "/images/restaurants/down-south/items/poori-sagu.jpg",
      "restaurantId": 4,
      "id": "21"
    },
    {
      "id": "d15f",
      "name": "puri sagu",
      "price": 45,
      "description": "sdkn;slghjs;lfsd;faIdf;lzskvjxlvbnxvmbn,vnbdfzsdlf jkf;wugfhesro;ghrouguh rlg her;oghre grsheg arhg;rgh",
      "imageUrl": "/images/restaurants/down-south/items/poori-sagu.jpg",
      "restaurantId": 1
    },
    {
      "id": "0ae6",
      "name": "bhel",
      "price": 50,
      "description": "dljfhdflshdfjdf wjfhsdjfhs fjd;fsdjf;lsdfj;eifofi jfuwhf uwfhuho ",
      "imageUrl": "https://tse3.mm.bing.net/th?id=OIP.tc2Wfg_OzyHlRDxWgFfF9wHaE8&pid=Api&P=0&h=180",
      "restaurantId": 1
    },
    {
      "id": "3c77",
      "name": "churma",
      "price": 33,
      "description": "dfdfdsfsfsfsdf sdfsdfsdf sdf sfsdf sdf df s fsdf sdf fds fs fsdf ",
      "imageUrl": "https://tse3.mm.bing.net/th?id=OIP.tc2Wfg_OzyHlRDxWgFfF9wHaE8&pid=Api&P=0&h=180",
      "restaurantId": 1
    }
  ],
  "orders": [
    {
      "id": "1",
      "restaurantId": 1,
      "items": [
        {
          "itemId": 1,
          "quantity": 2
        },
        {
          "itemId": 2,
          "quantity": 3
        }
      ]
    }
  ],
  "image-sources": []
}